{
  "date": "2026-07-17",
  "time": "09:58:22",
  "floatplane_link": "https://www.floatplane.com/post/XvvTZY1mBB?a=3TgkgKQ11H",
  "songs": [
    {
      "time": "00:11:03",
      "artist": "Martin Landström",
      "song_title": "For Better or Worse"
    },
    {
      "time": "00:14:18",
      "artist": "Martin Landström",
      "song_title": "For Better or Worse"
    },
    {
      "time": "00:18:34",
      "artist": "Bill McClintock",
      "song_title": "Hip to Be the Sandman"
    },
    {
      "time": "00:24:00",
      "artist": "Gran Turismo 3",
      "song_title": "Slipstream"
    },
    {
      "time": "00:26:43",
      "artist": "Aunty Donna",
      "song_title": "Hotdogs for Breakfast"
    },
    {
      "time": "00:30:12",
      "artist": "ALEJANDRO OTERO REIGADA",
      "song_title": "Love Me"
    },
    {
      "time": "00:32:52",
      "artist": "Esther Abrami",
      "song_title": "No.9 Frank's Waltz"
    },
    {
      "time": "00:33:38",
      "artist": "ALEJANDRO OTERO REIGADA",
      "song_title": "Love Me"
    },
    {
      "time": "00:36:57",
      "artist": "Macintosh plus",
      "song_title": "リサフランク420 / 現代のコンピュー"
    },
    {
      "time": "00:38:11",
      "artist": "Esther Abrami",
      "song_title": "No.9 Frank's Waltz"
    },
    {
      "time": "00:38:30",
      "artist": "Macintosh plus",
      "song_title": "リサフランク420 / 現代のコンピュー"
    },
    {
      "time": "00:41:56",
      "artist": "Martin Landström",
      "song_title": "Tablespoons"
    },
    {
      "time": "00:47:12",
      "artist": "Marvel Vs Capcom 2",
      "song_title": "Player Select"
    },
    {
      "time": "00:48:27",
      "artist": "Tim and Eric",
      "song_title": "A perfect dad day"
    },
    {
      "time": "00:50:27",
      "artist": "Halo",
      "song_title": "Theme song"
    },
    {
      "time": "00:58:34",
      "artist": "Ghost and Gooblings",
      "song_title": "Haunted Graveyard"
    }
  ],
  "events": []
}
